matplotlibstyles/__init__.py
matplotlibstyles/_version.py
matplotlibstyles/plotutils.py
matplotlibstyles/styles.py
matplotlibstyles-0.2.2.dist-info/LICENSE.txt
matplotlibstyles-0.2.2.dist-info/METADATA
matplotlibstyles-0.2.2.dist-info/WHEEL
matplotlibstyles-0.2.2.dist-info/top_level.txt
matplotlibstyles-0.2.2.dist-info/RECORD
