Metadata-Version: 2.1
Name: matplotlibstyles
Version: 0.2.2
Summary: Styles and helper functions for matplotlib
Home-page: https://github.com/cumberworth/matplotlibstyles
Author: Alexander Cumberworth
Author-email: alex@cumberworth.org
Classifier: Programming Language :: Python :: 3
Classifier: License :: OSI Approved :: MIT License
Classifier: Operating System :: POSIX :: Linux
Requires-Python: >=3
License-File: LICENSE.txt
Requires-Dist: matplotlib
Requires-Dist: numpy
